{
  "game_id": "s5i5",
  "total_levels": 8,
  "levels": [
    {
      "level": 0,
      "solved": true,
      "num_actions": 13,
      "actions": [
        {
          "id": 6,
          "data": {
            "x": 44,
            "y": 20
          }
        },
        {
          "id": 6,
          "data": {
            "x": 44,
            "y": 20
          }
        },
        {
          "id": 6,
          "data": {
            "x": 44,
            "y": 20
          }
        },
        {
          "id": 6,
          "data": {
            "x": 44,
            "y": 20
          }
        },
        {
          "id": 6,
          "data": {
            "x": 44,
            "y": 20
          }
        },
        {
          "id": 6,
          "data": {
            "x": 44,
            "y": 20
          }
        },
        {
          "id": 6,
          "data": {
            "x": 44,
            "y": 20
          }
        },
        {
          "id": 6,
          "data": {
            "x": 24,
            "y": 44
          }
        },
        {
          "id": 6,
          "data": {
            "x": 24,
            "y": 44
          }
        },
        {
          "id": 6,
          "data": {
            "x": 24,
            "y": 44
          }
        },
        {
          "id": 6,
          "data": {
            "x": 24,
            "y": 44
          }
        },
        {
          "id": 6,
          "data": {
            "x": 24,
            "y": 44
          }
        },
        {
          "id": 6,
          "data": {
            "x": 24,
            "y": 44
          }
        }
      ]
    },
    {
      "level": 1,
      "solved": false
    }
  ],
  "solved_levels": 1
}